idgen_alpha/__init__.py
idgen_alpha/_utils.py
idgen_alpha/idgenerator.py
idgen_alpha-0.1.0.dist-info/METADATA
idgen_alpha-0.1.0.dist-info/WHEEL
idgen_alpha-0.1.0.dist-info/RECORD
