Metadata-Version: 2.1
Name: idgen-alpha
Version: 0.1.0
Summary: 
Author: tnahddisttud
Author-email: siddhantp73@gmail.com
Requires-Python: >=3.12,<4.0
Classifier: Programming Language :: Python :: 3
Classifier: Programming Language :: Python :: 3.12
Requires-Dist: bson (>=0.5.10,<0.6.0)
